sphinx_github_style/__init__.py
sphinx_github_style/add_linkcode_class.py
sphinx_github_style/github_style.py
sphinx_github_style/lexer.py
sphinx_github_style/_static/github_style.css
sphinx_github_style/utils/__init__.py
sphinx_github_style/utils/git.py
sphinx_github_style/utils/linkcode.py
sphinx_github_style/utils/sphinx.py
sphinx_github_style-1.2.2.dist-info/LICENSE
sphinx_github_style-1.2.2.dist-info/METADATA
sphinx_github_style-1.2.2.dist-info/WHEEL
sphinx_github_style-1.2.2.dist-info/top_level.txt
sphinx_github_style-1.2.2.dist-info/RECORD
