Metadata-Version: 2.1
Name: sphinx-github-style
Version: 1.2.2
Summary: GitHub source code links and syntax highlighting for Sphinx documentation
Home-page: https://github.com/tdkorn/sphinx-github-style
Author: Adam Korn
Author-email: hello@dailykitten.net
License: MIT License
Download-URL: https://github.com/TDKorn/sphinx-github-style/tarball/master
Keywords: sphinx,sphinx-extension,sphinx-theme,pygments,pygments-style,github,linkcode
Platform: UNKNOWN
Classifier: Framework :: Sphinx :: Extension
Classifier: License :: OSI Approved :: MIT License
Classifier: Programming Language :: Python :: 3
Classifier: Programming Language :: Python :: 3.10
License-File: LICENSE
Requires-Dist: sphinx (>=1.8)
